{
    "name": "PerformanceAudit",
    "description": "Daily performance audits of all your sites in Matomo.",
    "version": "2.0.0",
    "theme": false,
    "require": {
        "php": ">=7.2.5",
        "matomo": ">=4.0.0-b1,<5.0.0-b1"
    },
    "authors": [
        {
            "name": "DevDavido",
            "homepage": "https://github.com/DevDavido"
        }
    ],
    "support": {
        "email": "github{at}diskoboss{døt}de",
        "issues": "https://github.com/DevDavido/performance-audit-plugin/issues"
    },
    "homepage": "https://github.com/DevDavido/performance-audit-plugin",
    "license": "GPL-3.0+",
    "keywords": [
        "performance",
        "audit",
        "monitor",
        "measure",
        "report",
        "lighthouse",
        "web vitals",
        "first contentful paint",
        "speed index",
        "largest contentful paint",
        "interactive",
        "time to interactive",
        "total blocking time",
        "cumulative layout shift"
    ]
}
